[
  {
    "Шафи металеві": [
      {
        "Шафи металеві для одягу(ШОМ)": [
          {
            "Однорівневі(ШОМ-1)": [
              {
                "Шафа металева для одягу однорівнева ШОМ 1/30/1 (RAL 7035)": [
                  { "Ширина секції, мм": [300, 400] },
                  {
                    "Колір": [
                      "Сірий (RAL 7035)",
                      "Червоний (RAL 3020)",
                      "Жовтий (RAL 1018)",
                      "Синій (RAL 5005)"
                    ]
                  },
                  {
                    "Замок": [
                      { "Механічний замок з двома ключами": [{ "Додаток до ціни": 0 }] },
                      {
                        "Механічний замок підвищеної секретності ( 2000 комбіінаційз двома ключами": [
                          { "Додаток до ціни": 25 }
                        ]
                      },
                      { "Петлі під навісний замок": [{ "Додаток до ціни": 25 }] },
                      { "Електронний замок": [{ "Додаток до ціни": 200 }] }
                    ]
                  },
                  { "price": 2360 }
                ]
              },
              {
                "Шафа металева для одягу однорівнева ШОМ 1/30/2 (RAL 7035)": [
                  { "Ширина секції, мм": [300, 400] },
                  {
                    "Колір": [
                      "Сірий (RAL 7035)",
                      "Червоний (RAL 3020)",
                      "Жовтий (RAL 1018)",
                      "Синій (RAL 5005)"
                    ]
                  },
                  {
                    "Замок": [
                      { "Механічний замок з двома ключами": [{ "Додаток до ціни": 0 }] },
                      {
                        "Механічний замок підвищеної секретності ( 2000 комбіінаційз двома ключами": [
                          { "Додаток до ціни": 50 }
                        ]
                      },
                      { "Петлі під навісний замок": [{ "Додаток до ціни": 50 }] },
                      { "Електронний замок": [{ "Додаток до ціни": 400 }] }
                    ]
                  },
                  { "price": 4310 }
                ]
              },
              {
                "Шафа металева для одягу однорівнева ШОМ 1/30/3 (RAL 7035)": [
                  { "Ширина секції, мм": [300, 400] },
                  {
                    "Колір": [
                      "Сірий (RAL 7035)",
                      "Червоний (RAL 3020)",
                      "Жовтий (RAL 1018)",
                      "Синій (RAL 5005)"
                    ]
                  },
                  {
                    "Замок": [
                      { "Механічний замок з двома ключами": [{ "Додаток до ціни": 0 }] },
                      {
                        "Механічний замок підвищеної секретності ( 2000 комбіінаційз двома ключами": [
                          { "Додаток до ціни": 75 }
                        ]
                      },
                      { "Петлі під навісний замок": [{ "Додаток до ціни": 75 }] },
                      { "Електронний замок": [{ "Додаток до ціни": 600 }] }
                    ]
                  },
                  { "price": 6260 }
                ]
              },
              {
                "Шафа металева для одягу однорівнева ШОМ 1/30/4 (RAL 7035)": [
                  { "Ширина секції, мм": [300, 400] },
                  {
                    "Колір": [
                      "Сірий (RAL 7035)",
                      "Червоний (RAL 3020)",
                      "Жовтий (RAL 1018)",
                      "Синій (RAL 5005)"
                    ]
                  },
                  {
                    "Замок": [
                      { "Механічний замок з двома ключами": [{ "Додаток до ціни": 0 }] },
                      {
                        "Механічний замок підвищеної секретності ( 2000 комбіінаційз двома ключами": [
                          { "Додаток до ціни": 100 }
                        ]
                      },
                      { "Петлі під навісний замок": [{ "Додаток до ціни": 100 }] },
                      { "Електронний замок": [{ "Додаток до ціни": 800 }] }
                    ]
                  },
                  { "price": 8210 }
                ]
              }
            ]
          },
          {
            "Однорівневі з перегородкою і додатковою нижньою поличкою (ШОМ П)": [
              {
                "Шафа металева для одягу однорівнева з перегородкою і з додатковою нижньою поличкою ШОМ-П 1/40/1 (RAL 7035)": [
                  { "Ширина": 400 },
                  {
                    "Колір": [
                      "Сірий (RAL 7035)",
                      "Червоний (RAL 3020)",
                      "Жовтий (RAL 1018)",
                      "Синій (RAL 5005)"
                    ]
                  },
                  {
                    "Замок": [
                      { "Механічний замок з двома ключами": [{ "Додаток до ціни": 0 }] },
                      {
                        "Механічний замок підвищеної секретності ( 2000 комбіінаційз двома ключами": [
                          { "Додаток до ціни": 25 }
                        ]
                      },
                      { "Петлі під навісний замок": [{ "Додаток до ціни": 25 }] },
                      { "Електронний замок": [{ "Додаток до ціни": 200 }] }
                    ]
                  },
                  { "price": 3100 }
                ],
                "Шафа металева для одягу однорівнева з перегородкою і з додатковою нижньою поличкою ШОМ-П 1/40/2 (RAL 7035)": [
                  { "Ширина": 400 },
                  {
                    "Колір": [
                      "Сірий (RAL 7035)",
                      "Червоний (RAL 3020)",
                      "Жовтий (RAL 1018)",
                      "Синій (RAL 5005)"
                    ]
                  },
                  {
                    "Замок": [
                      { "Механічний замок з двома ключами": [{ "Додаток до ціни": 0 }] },
                      {
                        "Механічний замок підвищеної секретності ( 2000 комбіінаційз двома ключами": [
                          { "Додаток до ціни": 50 }
                        ]
                      },
                      { "Петлі під навісний замок": [{ "Додаток до ціни": 50 }] },
                      { "Електронний замок": [{ "Додаток до ціни": 400 }] }
                    ]
                  },
                  { "price": 5790 }
                ],
                "Шафа металева для одягу однорівнева з перегородкою і з додатковою нижньою поличкою ШОМ-П 1/40/3 (RAL 7035)": [
                  { "Ширина": 400 },
                  {
                    "Колір": [
                      "Сірий (RAL 7035)",
                      "Червоний (RAL 3020)",
                      "Жовтий (RAL 1018)",
                      "Синій (RAL 5005)"
                    ]
                  },
                  {
                    "Замок": [
                      { "Механічний замок з двома ключами": [{ "Додаток до ціни": 0 }] },
                      {
                        "Механічний замок підвищеної секретності ( 2000 комбіінаційз двома ключами": [
                          { "Додаток до ціни": 75 }
                        ]
                      },
                      { "Петлі під навісний замок": [{ "Додаток до ціни": 75 }] },
                      { "Електронний замок": [{ "Додаток до ціни": 600 }] }
                    ]
                  },
                  { "price": 8480 }
                ],
                "Шафа металева для одягу однорівнева з перегородкою і з додатковою нижньою поличкою ШОМ-П 1/40/4 (RAL 7035)": [
                  { "Ширина": 400 },
                  {
                    "Колір": [
                      "Сірий (RAL 7035)",
                      "Червоний (RAL 3020)",
                      "Жовтий (RAL 1018)",
                      "Синій (RAL 5005)"
                    ]
                  },
                  {
                    "Замок": [
                      { "Механічний замок з двома ключами": [{ "Додаток до ціни": 0 }] },
                      {
                        "Механічний замок підвищеної секретності ( 2000 комбіінаційз двома ключами": [
                          { "Додаток до ціни": 100 }
                        ]
                      },
                      { "Петлі під навісний замок": [{ "Додаток до ціни": 100 }] },
                      { "Електронний замок": [{ "Додаток до ціни": 800 }] }
                    ]
                  },
                  { "price": 11170 }
                ]
              }
            ]
          },
          {
            "Однорівневі з додатковою нижньою поличкою (ШОМ нп 1)": [
              {
                "1": [{ "Ширина": [300, 400] }, { "Колір": ["red", "blue", "gray", "yellow"] }],
                "2": [{ "Ширина": [300, 400] }, { "Колір": ["red", "blue", "gray", "yellow"] }],
                "3": [{ "Ширина": [300, 400] }, { "Колір": ["red", "blue", "gray", "yellow"] }],
                "4": [{ "Ширина": [300, 400] }, { "Колір": ["red", "blue", "gray", "yellow"] }]
              }
            ]
          }
        ]
      }
    ],
    "Поштові скриньки": [
      {
        "Модель E1": [
          {
            "1": [
              { "Кількість секцій": [1, 2, 3, 4, 5, 6, 7, 8, 9, 10] },
              { "Колір": ["RAL7035", "RAL7016", "RAL10001"] }
            ],
            "2": [
              { "Кількість секцій": [1, 2, 3, 4, 5, 6, 7, 8, 9, 10] },
              { "Колір": ["red", "blue", "gray", "yellow"] }
            ],
            "3": [
              { "Кількість секцій": [1, 2, 3, 4, 5, 6, 7, 8, 9, 10] },
              { "Колір": ["red", "blue", "gray", "yellow"] }
            ],
            "4": [
              { "Кількість секцій": [1, 2, 3, 4, 5, 6, 7, 8, 9, 10] },
              { "Колір": ["red", "blue", "gray", "yellow"] }
            ]
          }
        ]
      },
      {
        "Модель E2": [
          {
            "1": [
              { "Кількість секцій": [1, 2, 3, 4, 5, 6, 7, 8, 9, 10] },
              { "Колір": ["RAL7035", "RAL7016", "RAL10001"] }
            ],
            "2": [
              { "Кількість секцій": [1, 2, 3, 4, 5, 6, 7, 8, 9, 10] },
              { "Колір": ["red", "blue", "gray", "yellow"] }
            ],
            "3": [
              { "Кількість секцій": [1, 2, 3, 4, 5, 6, 7, 8, 9, 10] },
              { "Колір": ["red", "blue", "gray", "yellow"] }
            ],
            "4": [
              { "Кількість секцій": [1, 2, 3, 4, 5, 6, 7, 8, 9, 10] },
              { "Колір": ["red", "blue", "gray", "yellow"] }
            ]
          }
        ]
      },
      {
        "Модель ЯП": [
          {
            "1": [
              { "Кількість секцій": [1, 2, 3, 4, 5, 6, 7, 8, 9, 10] },
              { "Колір": ["RAL7035", "RAL7016", "RAL10001"] }
            ],
            "2": [
              { "Кількість секцій": [1, 2, 3, 4, 5, 6, 7, 8, 9, 10] },
              { "Колір": ["red", "blue", "gray", "yellow"] }
            ],
            "3": [
              { "Кількість секцій": [1, 2, 3, 4, 5, 6, 7, 8, 9, 10] },
              { "Колір": ["red", "blue", "gray", "yellow"] }
            ],
            "4": [
              { "Кількість секцій": [1, 2, 3, 4, 5, 6, 7, 8, 9, 10] },
              { "Колір": ["red", "blue", "gray", "yellow"] }
            ]
          }
        ]
      }
    ],
    "Шафи пожежні": [
      { "Під 1 кран-комплект ДУ-50(65)": [1, 2, 3, 4, 5, 6, 7] },
      { "Під 1 кран-комплект ДУ-50(65) з місцем для вогнегасників": [1, 2, 3, 4, 5, 6, 7] },
      { "Під 2 кран-комплекта ДУ-50(65) з місцем для вогнегасників": [1, 2, 3, 4, 5, 6, 7] }
    ],
    "Лавки гардеробні": [
      { "Лавки гардеробні ЛГ-1": [1, 2, 3] },
      { "Лавки гардеробні ЛО-4": [1, 2, 3] },
      { "Лавки гардеробні ЛГ-5": [1, 2, 3] }
    ],
    "Сейфи": [{ "Сейфи для зброї": [1, 2, 3] }, { "Сейфи офісні": [1, 2, 3] }],
    "Кріплення і захист зовнішнього блоку кондиціонера": [
      { "Екран для зовнішнього блоку кондиціонера": [1, 2, 3] },
      { "Кошик для зовнішнього блоку кондиціонера": [1, 2, 3] },
      { "Бокс для зовнішнього блоку кондиціонера": [1, 2, 3] }
    ]
  }
]
